{
  "nurses": [
    {
      "assignments": [
        {
          "day": 0,
          "rooms": [
            "r00",
            "r01",
            "r02",
            "r06",
            "r08"
          ],
          "shift": "late"
        },
        {
          "day": 1,
          "rooms": [
            "r00",
            "r01",
            "r03",
            "r06",
            "r08",
            "r11"
          ],
          "shift": "late"
        },
        {
          "day": 2,
          "rooms": [
            "r04",
            "r05",
            "r07",
            "r10",
            "r11",
            "r13",
            "r14"
          ],
          "shift": "night"
        },
        {
          "day": 3,
          "rooms": [
            "r02",
            "r04",
            "r05",
            "r07"
          ],
          "shift": "night"
        },
        {
          "day": 4,
          "rooms": [
            "r00",
            "r01",
            "r02",
            "r03",
            "r05",
            "r06",
            "r07",
            "r09"
          ],
          "shift": "night"
        },
        {
          "day": 5,
          "rooms": [
            "r00",
            "r01",
            "r02",
            "r03",
            "r05",
            "r06",
            "r07",
            "r09",
            "r11",
            "r12",
            "r13"
          ],
          "shift": "night"
        },
        {
          "day": 6,
          "rooms": [
            "r00",
            "r01",
            "r02",
            "r03",
            "r05",
            "r06",
            "r07",
            "r09",
            "r11",
            "r12",
            "r13"
          ],
          "shift": "night"
        },
        {
          "day": 8,
          "rooms": [
            "r02",
            "r07",
            "r08",
            "r09",
            "r10"
          ],
          "shift": "early"
        },
        {
          "day": 9,
          "rooms": [
            "r00",
            "r01",
            "r04",
            "r05",
            "r06",
            "r07",
            "r08"
          ],
          "shift": "night"
        },
        {
          "day": 10,
          "rooms": [
            "r00",
            "r01",
            "r04",
            "r05",
            "r06",
            "r07",
            "r08"
          ],
          "shift": "night"
        },
        {
          "day": 12,
          "rooms": [
            "r00",
            "r01",
            "r03",
            "r04",
            "r05",
            "r06",
            "r12"
          ],
          "shift": "night"
        }
      ],
      "id": "n000"
    },
    {
      "assignments": [
        {
          "day": 1,
          "rooms": [
            "r00",
            "r01",
            "r03",
            "r04",
            "r06",
            "r08",
            "r09",
            "r11",
            "r12"
          ],
          "shift": "night"
        },
        {
          "day": 2,
          "rooms": [
            "r00",
            "r01",
            "r03",
            "r06",
            "r08",
            "r09",
            "r12"
          ],
          "shift": "night"
        },
        {
          "day": 3,
          "rooms": [
            "r00",
            "r03",
            "r06",
            "r08",
            "r09",
            "r10",
            "r12"
          ],
          "shift": "night"
        },
        {
          "day": 5,
          "rooms": [
            "r03",
            "r12"
          ],
          "shift": "early"
        },
        {
          "day": 6,
          "rooms": [
            "r04",
            "r08",
            "r10",
            "r14"
          ],
          "shift": "night"
        },
        {
          "day": 8,
          "rooms": [
            "r11"
          ],
          "shift": "late"
        },
        {
          "day": 9,
          "rooms": [
            "r00",
            "r06",
            "r09",
            "r13"
          ],
          "shift": "late"
        },
        {
          "day": 11,
          "rooms": [
            "r03",
            "r04",
            "r06",
            "r09"
          ],
          "shift": "early"
        },
        {
          "day": 12,
          "rooms": [
            "r08",
            "r13"
          ],
          "shift": "late"
        }
      ],
      "id": "n001"
    },
    {
      "assignments": [
        {
          "day": 0,
          "rooms": [
            "r00",
            "r01",
            "r02",
            "r06",
            "r07",
            "r08",
            "r09"
          ],
          "shift": "early"
        },
        {
          "day": 1,
          "rooms": [
            "r00",
            "r01",
            "r03",
            "r06",
            "r07",
            "r08",
            "r09"
          ],
          "shift": "early"
        },
        {
          "day": 2,
          "rooms": [
            "r00",
            "r01",
            "r03",
            "r04",
            "r05",
            "r06",
            "r07",
            "r08",
            "r09"
          ],
          "shift": "early"
        },
        {
          "day": 3,
          "rooms": [
            "r00",
            "r02",
            "r03",
            "r04",
            "r05",
            "r06",
            "r08"
          ],
          "shift": "early"
        },
        {
          "day": 4,
          "rooms": [
            "r00",
            "r01",
            "r03",
            "r05"
          ],
          "shift": "late"
        },
        {
          "day": 5,
          "rooms": [
            "r00",
            "r01",
            "r03",
            "r05",
            "r07",
            "r09",
            "r10"
          ],
          "shift": "late"
        },
        {
          "day": 6,
          "rooms": [
            "r00",
            "r01",
            "r03",
            "r05",
            "r07",
            "r09"
          ],
          "shift": "late"
        },
        {
          "day": 8,
          "rooms": [
            "r11",
            "r14"
          ],
          "shift": "early"
        },
        {
          "day": 9,
          "rooms": [
            "r00",
            "r02",
            "r07",
            "r11"
          ],
          "shift": "early"
        },
        {
          "day": 10,
          "rooms": [
            "r00",
            "r02",
            "r04",
            "r07"
          ],
          "shift": "late"
        },
        {
          "day": 11,
          "rooms": [
            "r00",
            "r01",
            "r03",
            "r04",
            "r05",
            "r06",
            "r08",
            "r13"
          ],
          "shift": "night"
        },
        {
          "day": 13,
          "rooms": [
            "r00",
            "r01",
            "r03",
            "r04",
            "r06",
            "r07"
          ],
          "shift": "early"
        }
      ],
      "id": "n002"
    },
    {
      "assignments": [
        {
          "day": 0,
          "rooms": [
            "r07",
            "r09",
            "r11",
            "r12"
          ],
          "shift": "late"
        },
        {
          "day": 2,
          "rooms": [
            "r10",
            "r11",
            "r12",
            "r13",
            "r14"
          ],
          "shift": "early"
        },
        {
          "day": 3,
          "rooms": [
            "r07",
            "r09",
            "r10",
            "r11",
            "r12",
            "r14"
          ],
          "shift": "early"
        },
        {
          "day": 4,
          "rooms": [
            "r00",
            "r01",
            "r02",
            "r03",
            "r06",
            "r07",
            "r12",
            "r14"
          ],
          "shift": "early"
        },
        {
          "day": 5,
          "rooms": [
            "r00",
            "r01",
            "r02",
            "r06"
          ],
          "shift": "early"
        },
        {
          "day": 6,
          "rooms": [
            "r00",
            "r01",
            "r02",
            "r03",
            "r06"
          ],
          "shift": "early"
        },
        {
          "day": 7,
          "rooms": [
            "r00",
            "r01",
            "r02",
            "r03",
            "r04",
            "r05",
            "r07",
            "r09",
            "r10"
          ],
          "shift": "night"
        },
        {
          "day": 9,
          "rooms": [
            "r03",
            "r04",
            "r12",
            "r13"
          ],
          "shift": "early"
        },
        {
          "day": 10,
          "rooms": [
            "r14"
          ],
          "shift": "night"
        },
        {
          "day": 12,
          "rooms": [
            "r00",
            "r03"
          ],
          "shift": "early"
        },
        {
          "day": 13,
          "rooms": [
            "r04",
            "r06",
            "r07",
            "r08",
            "r13"
          ],
          "shift": "late"
        }
      ],
      "id": "n003"
    },
    {
      "assignments": [
        {
          "day": 0,
          "rooms": [
            "r02",
            "r07",
            "r13"
          ],
          "shift": "night"
        },
        {
          "day": 1,
          "rooms": [
            "r07",
            "r13",
            "r14"
          ],
          "shift": "night"
        },
        {
          "day": 7,
          "rooms": [
            "r02",
            "r07",
            "r10"
          ],
          "shift": "early"
        },
        {
          "day": 9,
          "rooms": [
            "r12",
            "r14"
          ],
          "shift": "night"
        },
        {
          "day": 10,
          "rooms": [
            "r12"
          ],
          "shift": "night"
        },
        {
          "day": 11,
          "rooms": [
            "r12",
            "r14"
          ],
          "shift": "night"
        },
        {
          "day": 13,
          "rooms": [
            "r08"
          ],
          "shift": "early"
        }
      ],
      "id": "n004"
    },
    {
      "assignments": [
        {
          "day": 0,
          "rooms": [
            "r00",
            "r01",
            "r06",
            "r08",
            "r09",
            "r11",
            "r12"
          ],
          "shift": "night"
        },
        {
          "day": 3,
          "rooms": [
            "r00",
            "r02",
            "r06"
          ],
          "shift": "late"
        },
        {
          "day": 4,
          "rooms": [
            "r02",
            "r06",
            "r13"
          ],
          "shift": "late"
        },
        {
          "day": 5,
          "rooms": [
            "r02",
            "r06",
            "r12",
            "r13"
          ],
          "shift": "late"
        },
        {
          "day": 6,
          "rooms": [
            "r02",
            "r06",
            "r12",
            "r13"
          ],
          "shift": "late"
        },
        {
          "day": 7,
          "rooms": [
            "r00",
            "r01",
            "r02",
            "r03",
            "r12"
          ],
          "shift": "late"
        },
        {
          "day": 8,
          "rooms": [
            "r00",
            "r01",
            "r02",
            "r03",
            "r12"
          ],
          "shift": "late"
        },
        {
          "day": 9,
          "rooms": [
            "r01",
            "r02",
            "r03"
          ],
          "shift": "late"
        },
        {
          "day": 11,
          "rooms": [
            "r07"
          ],
          "shift": "night"
        },
        {
          "day": 12,
          "rooms": [
            "r07",
            "r08",
            "r13",
            "r14"
          ],
          "shift": "night"
        },
        {
          "day": 13,
          "rooms": [
            "r00",
            "r01",
            "r04",
            "r06",
            "r07",
            "r08",
            "r13",
            "r14"
          ],
          "shift": "night"
        }
      ],
      "id": "n005"
    },
    {
      "assignments": [
        {
          "day": 1,
          "rooms": [
            "r14"
          ],
          "shift": "late"
        },
        {
          "day": 3,
          "rooms": [
            "r11",
            "r14"
          ],
          "shift": "night"
        },
        {
          "day": 4,
          "rooms": [
            "r04",
            "r08",
            "r10",
            "r11",
            "r12",
            "r13",
            "r14"
          ],
          "shift": "night"
        },
        {
          "day": 6,
          "rooms": [
            "r04",
            "r05",
            "r12",
            "r13"
          ],
          "shift": "early"
        },
        {
          "day": 7,
          "rooms": [
            "r00",
            "r01",
            "r03",
            "r04",
            "r05",
            "r12",
            "r14"
          ],
          "shift": "early"
        },
        {
          "day": 8,
          "rooms": [
            "r01",
            "r03",
            "r05",
            "r12"
          ],
          "shift": "early"
        },
        {
          "day": 9,
          "rooms": [
            "r13"
          ],
          "shift": "night"
        },
        {
          "day": 10,
          "rooms": [
            "r13"
          ],
          "shift": "night"
        },
        {
          "day": 12,
          "rooms": [
            "r04",
            "r06",
            "r08",
            "r09"
          ],
          "shift": "early"
        },
        {
          "day": 13,
          "rooms": [
            "r03",
            "r11"
          ],
          "shift": "late"
        }
      ],
      "id": "n006"
    },
    {
      "assignments": [
        {
          "day": 2,
          "rooms": [
            "r00",
            "r01",
            "r03",
            "r05",
            "r13"
          ],
          "shift": "late"
        },
        {
          "day": 5,
          "rooms": [
            "r04",
            "r08",
            "r10",
            "r14"
          ],
          "shift": "night"
        },
        {
          "day": 9,
          "rooms": [
            "r01",
            "r05",
            "r06"
          ],
          "shift": "early"
        },
        {
          "day": 11,
          "rooms": [
            "r07",
            "r08",
            "r11"
          ],
          "shift": "early"
        },
        {
          "day": 13,
          "rooms": [
            "r03",
            "r05",
            "r09",
            "r12"
          ],
          "shift": "night"
        }
      ],
      "id": "n007"
    },
    {
      "assignments": [
        {
          "day": 0,
          "rooms": [
            "r13"
          ],
          "shift": "late"
        },
        {
          "day": 1,
          "rooms": [
            "r04",
            "r07",
            "r09",
            "r12",
            "r13"
          ],
          "shift": "late"
        },
        {
          "day": 5,
          "rooms": [
            "r07",
            "r14"
          ],
          "shift": "early"
        },
        {
          "day": 6,
          "rooms": [
            "r07",
            "r08",
            "r09",
            "r10",
            "r11",
            "r14"
          ],
          "shift": "early"
        },
        {
          "day": 7,
          "rooms": [
            "r05",
            "r06",
            "r07",
            "r10"
          ],
          "shift": "late"
        },
        {
          "day": 8,
          "rooms": [
            "r05",
            "r06",
            "r07",
            "r08",
            "r10",
            "r14"
          ],
          "shift": "late"
        },
        {
          "day": 9,
          "rooms": [
            "r04",
            "r05",
            "r07",
            "r08",
            "r10",
            "r14"
          ],
          "shift": "late"
        },
        {
          "day": 11,
          "rooms": [
            "r00",
            "r02",
            "r03",
            "r04",
            "r07",
            "r13"
          ],
          "shift": "late"
        },
        {
          "day": 12,
          "rooms": [
            "r00",
            "r02",
            "r03",
            "r04",
            "r07"
          ],
          "shift": "late"
        },
        {
          "day": 13,
          "rooms": [
            "r00",
            "r02",
            "r09"
          ],
          "shift": "late"
        }
      ],
      "id": "n008"
    },
    {
      "assignments": [
        {
          "day": 7,
          "rooms": [
            "r11"
          ],
          "shift": "late"
        },
        {
          "day": 8,
          "rooms": [
            "r01",
            "r05",
            "r07",
            "r08",
            "r14"
          ],
          "shift": "night"
        },
        {
          "day": 10,
          "rooms": [
            "r05",
            "r08",
            "r10",
            "r12"
          ],
          "shift": "late"
        },
        {
          "day": 11,
          "rooms": [
            "r05",
            "r08",
            "r10",
            "r12"
          ],
          "shift": "late"
        },
        {
          "day": 12,
          "rooms": [
            "r05",
            "r10",
            "r12"
          ],
          "shift": "late"
        },
        {
          "day": 13,
          "rooms": [
            "r05",
            "r10",
            "r12"
          ],
          "shift": "late"
        }
      ],
      "id": "n009"
    },
    {
      "assignments": [
        {
          "day": 4,
          "rooms": [
            "r05",
            "r08",
            "r09",
            "r10",
            "r11"
          ],
          "shift": "early"
        },
        {
          "day": 5,
          "rooms": [
            "r05",
            "r08",
            "r09",
            "r10",
            "r11"
          ],
          "shift": "early"
        },
        {
          "day": 6,
          "rooms": [
            "r10",
            "r11"
          ],
          "shift": "late"
        },
        {
          "day": 7,
          "rooms": [
            "r06",
            "r08",
            "r11",
            "r12",
            "r13",
            "r14"
          ],
          "shift": "night"
        },
        {
          "day": 8,
          "rooms": [
            "r00",
            "r02",
            "r03",
            "r04",
            "r06",
            "r09",
            "r10",
            "r11",
            "r12",
            "r13"
          ],
          "shift": "night"
        },
        {
          "day": 9,
          "rooms": [
            "r02",
            "r03",
            "r09",
            "r10",
            "r11"
          ],
          "shift": "night"
        },
        {
          "day": 10,
          "rooms": [
            "r02",
            "r03",
            "r09",
            "r10",
            "r11"
          ],
          "shift": "night"
        },
        {
          "day": 11,
          "rooms": [
            "r02",
            "r09",
            "r10",
            "r11"
          ],
          "shift": "night"
        },
        {
          "day": 12,
          "rooms": [
            "r02",
            "r09",
            "r10",
            "r11"
          ],
          "shift": "night"
        },
        {
          "day": 13,
          "rooms": [
            "r02",
            "r10",
            "r11"
          ],
          "shift": "night"
        }
      ],
      "id": "n010"
    },
    {
      "assignments": [
        {
          "day": 3,
          "rooms": [
            "r05",
            "r07",
            "r08"
          ],
          "shift": "late"
        },
        {
          "day": 4,
          "rooms": [
            "r04",
            "r07",
            "r08"
          ],
          "shift": "late"
        },
        {
          "day": 7,
          "rooms": [
            "r06",
            "r08",
            "r11"
          ],
          "shift": "early"
        },
        {
          "day": 11,
          "rooms": [
            "r14"
          ],
          "shift": "early"
        }
      ],
      "id": "n011"
    },
    {
      "assignments": [
        {
          "day": 5,
          "rooms": [
            "r04",
            "r08",
            "r14"
          ],
          "shift": "late"
        },
        {
          "day": 6,
          "rooms": [
            "r04",
            "r08",
            "r14"
          ],
          "shift": "late"
        },
        {
          "day": 7,
          "rooms": [
            "r04",
            "r14"
          ],
          "shift": "late"
        },
        {
          "day": 8,
          "rooms": [
            "r04"
          ],
          "shift": "late"
        }
      ],
      "id": "n012"
    },
    {
      "assignments": [
        {
          "day": 0,
          "rooms": [
            "r13"
          ],
          "shift": "early"
        },
        {
          "day": 2,
          "rooms": [
            "r04",
            "r06",
            "r07",
            "r08"
          ],
          "shift": "late"
        },
        {
          "day": 10,
          "rooms": [
            "r00",
            "r03",
            "r04",
            "r10",
            "r12"
          ],
          "shift": "early"
        },
        {
          "day": 11,
          "rooms": [
            "r00",
            "r10",
            "r12"
          ],
          "shift": "early"
        }
      ],
      "id": "n013"
    },
    {
      "assignments": [
        {
          "day": 2,
          "rooms": [
            "r09",
            "r10",
            "r11",
            "r12"
          ],
          "shift": "late"
        },
        {
          "day": 3,
          "rooms": [
            "r03",
            "r04",
            "r09",
            "r12"
          ],
          "shift": "late"
        },
        {
          "day": 4,
          "rooms": [
            "r09",
            "r12"
          ],
          "shift": "late"
        },
        {
          "day": 10,
          "rooms": [
            "r01",
            "r06",
            "r09"
          ],
          "shift": "late"
        },
        {
          "day": 11,
          "rooms": [
            "r01",
            "r06",
            "r09"
          ],
          "shift": "late"
        },
        {
          "day": 12,
          "rooms": [
            "r01",
            "r06",
            "r09"
          ],
          "shift": "late"
        },
        {
          "day": 13,
          "rooms": [
            "r01"
          ],
          "shift": "late"
        }
      ],
      "id": "n014"
    },
    {
      "assignments": [
        {
          "day": 1,
          "rooms": [
            "r13"
          ],
          "shift": "early"
        },
        {
          "day": 10,
          "rooms": [
            "r11",
            "r14"
          ],
          "shift": "late"
        },
        {
          "day": 11,
          "rooms": [
            "r11",
            "r14"
          ],
          "shift": "late"
        },
        {
          "day": 12,
          "rooms": [
            "r11",
            "r14"
          ],
          "shift": "late"
        },
        {
          "day": 13,
          "rooms": [
            "r14"
          ],
          "shift": "late"
        }
      ],
      "id": "n015"
    },
    {
      "assignments": [
        {
          "day": 5,
          "rooms": [
            "r11"
          ],
          "shift": "late"
        },
        {
          "day": 7,
          "rooms": [
            "r09",
            "r13"
          ],
          "shift": "early"
        },
        {
          "day": 10,
          "rooms": [
            "r01",
            "r02"
          ],
          "shift": "early"
        },
        {
          "day": 11,
          "rooms": [
            "r01",
            "r02"
          ],
          "shift": "early"
        },
        {
          "day": 12,
          "rooms": [
            "r01",
            "r02"
          ],
          "shift": "early"
        }
      ],
      "id": "n016"
    },
    {
      "assignments": [
        {
          "day": 0,
          "rooms": [
            "r11",
            "r12"
          ],
          "shift": "early"
        },
        {
          "day": 2,
          "rooms": [
            "r14"
          ],
          "shift": "late"
        },
        {
          "day": 4,
          "rooms": [
            "r04",
            "r13"
          ],
          "shift": "early"
        },
        {
          "day": 5,
          "rooms": [
            "r04",
            "r13"
          ],
          "shift": "early"
        },
        {
          "day": 11,
          "rooms": [
            "r05",
            "r13"
          ],
          "shift": "early"
        },
        {
          "day": 13,
          "rooms": [
            "r02",
            "r10",
            "r11"
          ],
          "shift": "early"
        }
      ],
      "id": "n017"
    },
    {
      "assignments": [
        {
          "day": 3,
          "rooms": [
            "r10"
          ],
          "shift": "late"
        },
        {
          "day": 4,
          "rooms": [
            "r10"
          ],
          "shift": "late"
        }
      ],
      "id": "n018"
    },
    {
      "assignments": [
        {
          "day": 1,
          "rooms": [
            "r04",
            "r11",
            "r12"
          ],
          "shift": "early"
        },
        {
          "day": 3,
          "rooms": [
            "r11",
            "r14"
          ],
          "shift": "late"
        },
        {
          "day": 4,
          "rooms": [
            "r11",
            "r14"
          ],
          "shift": "late"
        }
      ],
      "id": "n019"
    },
    {
      "assignments": [
        {
          "day": 7,
          "rooms": [
            "r08",
            "r09",
            "r13"
          ],
          "shift": "late"
        },
        {
          "day": 8,
          "rooms": [
            "r09",
            "r13"
          ],
          "shift": "late"
        },
        {
          "day": 10,
          "rooms": [
            "r05",
            "r06",
            "r07"
          ],
          "shift": "early"
        }
      ],
      "id": "n021"
    },
    {
      "assignments": [
        {
          "day": 10,
          "rooms": [
            "r11",
            "r14"
          ],
          "shift": "early"
        }
      ],
      "id": "n022"
    },
    {
      "assignments": [
        {
          "day": 9,
          "rooms": [
            "r10",
            "r14"
          ],
          "shift": "early"
        }
      ],
      "id": "n023"
    },
    {
      "assignments": [
        {
          "day": 9,
          "rooms": [
            "r08",
            "r09"
          ],
          "shift": "early"
        },
        {
          "day": 10,
          "rooms": [
            "r08",
            "r09",
            "r13"
          ],
          "shift": "early"
        },
        {
          "day": 13,
          "rooms": [
            "r09",
            "r13",
            "r14"
          ],
          "shift": "early"
        }
      ],
      "id": "n024"
    },
    {
      "assignments": [
        {
          "day": 12,
          "rooms": [
            "r14"
          ],
          "shift": "early"
        }
      ],
      "id": "n025"
    },
    {
      "assignments": [
        {
          "day": 10,
          "rooms": [
            "r03",
            "r13"
          ],
          "shift": "late"
        },
        {
          "day": 12,
          "rooms": [
            "r05",
            "r10",
            "r13"
          ],
          "shift": "early"
        }
      ],
      "id": "n027"
    },
    {
      "assignments": [
        {
          "day": 13,
          "rooms": [
            "r05",
            "r12"
          ],
          "shift": "early"
        }
      ],
      "id": "n029"
    },
    {
      "assignments": [
        {
          "day": 1,
          "rooms": [
            "r14"
          ],
          "shift": "early"
        },
        {
          "day": 8,
          "rooms": [
            "r00",
            "r04",
            "r06",
            "r13"
          ],
          "shift": "early"
        },
        {
          "day": 9,
          "rooms": [
            "r11",
            "r12"
          ],
          "shift": "late"
        },
        {
          "day": 12,
          "rooms": [
            "r07",
            "r11",
            "r12"
          ],
          "shift": "early"
        }
      ],
      "id": "n030"
    }
  ],
  "patients": [
    {
      "admission_day": "none",
      "id": "p000"
    },
    {
      "admission_day": 11,
      "id": "p001",
      "operating_theater": "t1",
      "room": "r09"
    },
    {
      "admission_day": "none",
      "id": "p002"
    },
    {
      "admission_day": 11,
      "id": "p003",
      "operating_theater": "t0",
      "room": "r09"
    },
    {
      "admission_day": "none",
      "id": "p004"
    },
    {
      "admission_day": 1,
      "id": "p005",
      "operating_theater": "t2",
      "room": "r11"
    },
    {
      "admission_day": 11,
      "id": "p006",
      "operating_theater": "t0",
      "room": "r02"
    },
    {
      "admission_day": 6,
      "id": "p007",
      "operating_theater": "t1",
      "room": "r07"
    },
    {
      "admission_day": 2,
      "id": "p008",
      "operating_theater": "t0",
      "room": "r14"
    },
    {
      "admission_day": "none",
      "id": "p009"
    },
    {
      "admission_day": 13,
      "id": "p010",
      "operating_theater": "t0",
      "room": "r03"
    },
    {
      "admission_day": "none",
      "id": "p011"
    },
    {
      "admission_day": 2,
      "id": "p012",
      "operating_theater": "t0",
      "room": "r10"
    },
    {
      "admission_day": 2,
      "id": "p013",
      "operating_theater": "t0",
      "room": "r03"
    },
    {
      "admission_day": "none",
      "id": "p014"
    },
    {
      "admission_day": "none",
      "id": "p015"
    },
    {
      "admission_day": "none",
      "id": "p016"
    },
    {
      "admission_day": 3,
      "id": "p017",
      "operating_theater": "t1",
      "room": "r02"
    },
    {
      "admission_day": "none",
      "id": "p018"
    },
    {
      "admission_day": 6,
      "id": "p019",
      "operating_theater": "t2",
      "room": "r01"
    },
    {
      "admission_day": 3,
      "id": "p020",
      "operating_theater": "t0",
      "room": "r08"
    },
    {
      "admission_day": 2,
      "id": "p021",
      "operating_theater": "t1",
      "room": "r05"
    },
    {
      "admission_day": 1,
      "id": "p022",
      "operating_theater": "t2",
      "room": "r14"
    },
    {
      "admission_day": "none",
      "id": "p023"
    },
    {
      "admission_day": 4,
      "id": "p024",
      "operating_theater": "t0",
      "room": "r04"
    },
    {
      "admission_day": 3,
      "id": "p025",
      "operating_theater": "t1",
      "room": "r10"
    },
    {
      "admission_day": 12,
      "id": "p026",
      "operating_theater": "t2",
      "room": "r08"
    },
    {
      "admission_day": "none",
      "id": "p027"
    },
    {
      "admission_day": 3,
      "id": "p028",
      "operating_theater": "t1",
      "room": "r14"
    },
    {
      "admission_day": 9,
      "id": "p029",
      "operating_theater": "t2",
      "room": "r05"
    },
    {
      "admission_day": 11,
      "id": "p030",
      "operating_theater": "t1",
      "room": "r10"
    },
    {
      "admission_day": 6,
      "id": "p031",
      "operating_theater": "t0",
      "room": "r13"
    },
    {
      "admission_day": "none",
      "id": "p032"
    },
    {
      "admission_day": 13,
      "id": "p033",
      "operating_theater": "t0",
      "room": "r09"
    },
    {
      "admission_day": "none",
      "id": "p034"
    },
    {
      "admission_day": "none",
      "id": "p035"
    },
    {
      "admission_day": 12,
      "id": "p036",
      "operating_theater": "t2",
      "room": "r10"
    },
    {
      "admission_day": 7,
      "id": "p037",
      "operating_theater": "t0",
      "room": "r12"
    },
    {
      "admission_day": 2,
      "id": "p038",
      "operating_theater": "t1",
      "room": "r09"
    },
    {
      "admission_day": "none",
      "id": "p039"
    },
    {
      "admission_day": "none",
      "id": "p040"
    },
    {
      "admission_day": "none",
      "id": "p041"
    },
    {
      "admission_day": 1,
      "id": "p042",
      "operating_theater": "t2",
      "room": "r04"
    },
    {
      "admission_day": 7,
      "id": "p043",
      "operating_theater": "t1",
      "room": "r04"
    },
    {
      "admission_day": "none",
      "id": "p044"
    },
    {
      "admission_day": "none",
      "id": "p045"
    },
    {
      "admission_day": "none",
      "id": "p046"
    },
    {
      "admission_day": "none",
      "id": "p047"
    },
    {
      "admission_day": "none",
      "id": "p048"
    },
    {
      "admission_day": 13,
      "id": "p049",
      "operating_theater": "t2",
      "room": "r13"
    },
    {
      "admission_day": 6,
      "id": "p050",
      "operating_theater": "t2",
      "room": "r06"
    },
    {
      "admission_day": "none",
      "id": "p051"
    },
    {
      "admission_day": "none",
      "id": "p052"
    },
    {
      "admission_day": "none",
      "id": "p053"
    },
    {
      "admission_day": 8,
      "id": "p054",
      "operating_theater": "t2",
      "room": "r07"
    },
    {
      "admission_day": "none",
      "id": "p055"
    },
    {
      "admission_day": 10,
      "id": "p056",
      "operating_theater": "t0",
      "room": "r11"
    },
    {
      "admission_day": 13,
      "id": "p057",
      "operating_theater": "t2",
      "room": "r00"
    },
    {
      "admission_day": 8,
      "id": "p058",
      "operating_theater": "t2",
      "room": "r01"
    },
    {
      "admission_day": 9,
      "id": "p059",
      "operating_theater": "t0",
      "room": "r06"
    },
    {
      "admission_day": "none",
      "id": "p060"
    },
    {
      "admission_day": "none",
      "id": "p061"
    },
    {
      "admission_day": "none",
      "id": "p062"
    },
    {
      "admission_day": "none",
      "id": "p063"
    },
    {
      "admission_day": 4,
      "id": "p064",
      "operating_theater": "t2",
      "room": "r07"
    },
    {
      "admission_day": "none",
      "id": "p065"
    },
    {
      "admission_day": 9,
      "id": "p066",
      "operating_theater": "t0",
      "room": "r14"
    },
    {
      "admission_day": "none",
      "id": "p067"
    },
    {
      "admission_day": "none",
      "id": "p068"
    },
    {
      "admission_day": "none",
      "id": "p069"
    },
    {
      "admission_day": "none",
      "id": "p070"
    },
    {
      "admission_day": 11,
      "id": "p071",
      "operating_theater": "t1",
      "room": "r00"
    },
    {
      "admission_day": 11,
      "id": "p072",
      "operating_theater": "t0",
      "room": "r03"
    },
    {
      "admission_day": "none",
      "id": "p073"
    },
    {
      "admission_day": 12,
      "id": "p074",
      "operating_theater": "t2",
      "room": "r08"
    },
    {
      "admission_day": "none",
      "id": "p075"
    },
    {
      "admission_day": "none",
      "id": "p076"
    },
    {
      "admission_day": 7,
      "id": "p077",
      "operating_theater": "t0",
      "room": "r12"
    },
    {
      "admission_day": "none",
      "id": "p078"
    },
    {
      "admission_day": 3,
      "id": "p079",
      "operating_theater": "t0",
      "room": "r05"
    },
    {
      "admission_day": "none",
      "id": "p080"
    },
    {
      "admission_day": "none",
      "id": "p081"
    },
    {
      "admission_day": "none",
      "id": "p082"
    },
    {
      "admission_day": "none",
      "id": "p083"
    },
    {
      "admission_day": 4,
      "id": "p084",
      "operating_theater": "t0",
      "room": "r13"
    },
    {
      "admission_day": 6,
      "id": "p085",
      "operating_theater": "t0",
      "room": "r08"
    },
    {
      "admission_day": 9,
      "id": "p086",
      "operating_theater": "t2",
      "room": "r11"
    },
    {
      "admission_day": "none",
      "id": "p087"
    },
    {
      "admission_day": 13,
      "id": "p088",
      "operating_theater": "t0",
      "room": "r02"
    },
    {
      "admission_day": 12,
      "id": "p089",
      "operating_theater": "t2",
      "room": "r12"
    },
    {
      "admission_day": "none",
      "id": "p090"
    },
    {
      "admission_day": "none",
      "id": "p091"
    },
    {
      "admission_day": 7,
      "id": "p092",
      "operating_theater": "t0",
      "room": "r01"
    },
    {
      "admission_day": "none",
      "id": "p093"
    },
    {
      "admission_day": 10,
      "id": "p094",
      "operating_theater": "t0",
      "room": "r00"
    },
    {
      "admission_day": "none",
      "id": "p095"
    },
    {
      "admission_day": 3,
      "id": "p096",
      "operating_theater": "t0",
      "room": "r06"
    },
    {
      "admission_day": 13,
      "id": "p097",
      "operating_theater": "t0",
      "room": "r05"
    },
    {
      "admission_day": "none",
      "id": "p098"
    },
    {
      "admission_day": 4,
      "id": "p099",
      "operating_theater": "t2",
      "room": "r13"
    },
    {
      "admission_day": "none",
      "id": "p100"
    },
    {
      "admission_day": "none",
      "id": "p101"
    },
    {
      "admission_day": 12,
      "id": "p102",
      "operating_theater": "t2",
      "room": "r07"
    },
    {
      "admission_day": "none",
      "id": "p103"
    },
    {
      "admission_day": 8,
      "id": "p104",
      "operating_theater": "t2",
      "room": "r08"
    },
    {
      "admission_day": "none",
      "id": "p105"
    },
    {
      "admission_day": 7,
      "id": "p106",
      "operating_theater": "t0",
      "room": "r13"
    },
    {
      "admission_day": "none",
      "id": "p107"
    },
    {
      "admission_day": "none",
      "id": "p108"
    },
    {
      "admission_day": 10,
      "id": "p109",
      "operating_theater": "t0",
      "room": "r14"
    },
    {
      "admission_day": "none",
      "id": "p110"
    },
    {
      "admission_day": 8,
      "id": "p111",
      "operating_theater": "t2",
      "room": "r14"
    }
  ]
}